clients_scanner/__init__.py
clients_scanner/__main__.py
clients_scanner/__version__.py
clients_scanner/clients_scanner.py
clients_scanner/config.py
clients_scanner/deauth.py
clients_scanner/logger.py
clients_scanner/matcher.py
clients_scanner/scanner.py
clients_scanner/scrolled_frame.py
clients_scanner/utils.py
clients_scanner/images/day_mode.png
clients_scanner/images/debug.png
clients_scanner/images/laptop.png
clients_scanner/images/night_mode.png
clients_scanner/images/pc.png
clients_scanner/images/phone.png
clients_scanner/images/raspberry.png
clients_scanner/images/router.png
clients_scanner/images/scan_off.png
clients_scanner/images/scan_on.png
clients_scanner/images/sound_off.png
clients_scanner/images/sound_on.png
clients_scanner/images/watch.png
clients_scanner/sounds/mixkit-long-pop-2358.wav
clients_scanner/sounds/mixkit-message-pop-alert-2354.mp3
clients_scanner-0.1.2.dist-info/LICENSE.txt
clients_scanner-0.1.2.dist-info/METADATA
clients_scanner-0.1.2.dist-info/WHEEL
clients_scanner-0.1.2.dist-info/entry_points.txt
clients_scanner-0.1.2.dist-info/top_level.txt
clients_scanner-0.1.2.dist-info/RECORD
