Metadata-Version: 2.1
Name: clients-scanner
Version: 0.1.2
Summary: Local network clients scanner with deauth feature
Home-page: https://github.com/streanger/clients_scanner
Author: streanger
Author-email: divisionexe@gmail.com
License: MIT
Platform: UNKNOWN
Classifier: Programming Language :: Python :: 3
Classifier: License :: OSI Approved :: MIT License
Classifier: Operating System :: Microsoft :: Windows
Classifier: Operating System :: POSIX :: Linux
License-File: LICENSE.txt
Requires-Dist: aiofiles (==23.1.0)
Requires-Dist: aiohttp (==3.8.4)
Requires-Dist: aiosignal (==1.3.1)
Requires-Dist: async-timeout (==4.0.2)
Requires-Dist: attrs (==22.2.0)
Requires-Dist: charset-normalizer (==3.0.1)
Requires-Dist: frozenlist (==1.3.3)
Requires-Dist: idna (==3.4)
Requires-Dist: mac-vendor-lookup (==0.1.12)
Requires-Dist: multidict (==6.0.4)
Requires-Dist: Pillow (==9.4.0)
Requires-Dist: playsound (==1.2.2)
Requires-Dist: scapy (==2.5.0)
Requires-Dist: termcolor (==2.2.0)
Requires-Dist: yarl (==1.8.2)
